alchemtest/__init__.py
alchemtest/_version.py
alchemtest/amber/__init__.py
alchemtest/amber/access.py
alchemtest/amber/bace_CAT-13d~CAT-17a/descr.rst
alchemtest/amber/bace_CAT-13d~CAT-17a/complex/decharge/0.00/ti-0.00.out.bz2
alchemtest/amber/bace_CAT-13d~CAT-17a/complex/decharge/0.25/ti-0.25.out.bz2
alchemtest/amber/bace_CAT-13d~CAT-17a/complex/decharge/0.50/ti-0.50.out.bz2
alchemtest/amber/bace_CAT-13d~CAT-17a/complex/decharge/0.75/ti-0.75.out.bz2
alchemtest/amber/bace_CAT-13d~CAT-17a/complex/decharge/1.00/ti-1.00.out.bz2
alchemtest/amber/bace_CAT-13d~CAT-17a/complex/recharge/0.00/ti-0.00.out.bz2
alchemtest/amber/bace_CAT-13d~CAT-17a/complex/recharge/0.25/ti-0.25.out.bz2
alchemtest/amber/bace_CAT-13d~CAT-17a/complex/recharge/0.50/ti-0.50.out.bz2
alchemtest/amber/bace_CAT-13d~CAT-17a/complex/recharge/0.75/ti-0.75.out.bz2
alchemtest/amber/bace_CAT-13d~CAT-17a/complex/recharge/1.00/ti-1.00.out.bz2
alchemtest/amber/bace_CAT-13d~CAT-17a/complex/vdw/0.0/ti-0.0.out.bz2
alchemtest/amber/bace_CAT-13d~CAT-17a/complex/vdw/0.0479/ti-0.0479.out.bz2
alchemtest/amber/bace_CAT-13d~CAT-17a/complex/vdw/0.1150/ti-0.1150.out.bz2
alchemtest/amber/bace_CAT-13d~CAT-17a/complex/vdw/0.2063/ti-0.2063.out.bz2
alchemtest/amber/bace_CAT-13d~CAT-17a/complex/vdw/0.3160/ti-0.3160.out.bz2
alchemtest/amber/bace_CAT-13d~CAT-17a/complex/vdw/0.4373/ti-0.4373.out.bz2
alchemtest/amber/bace_CAT-13d~CAT-17a/complex/vdw/0.5626/ti-0.5626.out.bz2
alchemtest/amber/bace_CAT-13d~CAT-17a/complex/vdw/0.6839/ti-0.6839.out.bz2
alchemtest/amber/bace_CAT-13d~CAT-17a/complex/vdw/0.7936/ti-0.7936.out.bz2
alchemtest/amber/bace_CAT-13d~CAT-17a/complex/vdw/0.8849/ti-0.8849.out.bz2
alchemtest/amber/bace_CAT-13d~CAT-17a/complex/vdw/0.9520/ti-0.9520.out.bz2
alchemtest/amber/bace_CAT-13d~CAT-17a/complex/vdw/1.0/ti-1.0.out.bz2
alchemtest/amber/bace_CAT-13d~CAT-17a/solvated/decharge/0.00/ti-0.00.out.bz2
alchemtest/amber/bace_CAT-13d~CAT-17a/solvated/decharge/0.25/ti-0.25.out.bz2
alchemtest-0.8.0.dist-info/LICENSE
alchemtest-0.8.0.dist-info/METADATA
alchemtest-0.8.0.dist-info/WHEEL
alchemtest-0.8.0.dist-info/top_level.txt
alchemtest-0.8.0.dist-info/RECORD
